linear_matrix/__init__.py
linear_matrix/matrix.py
linear_matrix-1.0.dist-info/METADATA
linear_matrix-1.0.dist-info/WHEEL
linear_matrix-1.0.dist-info/top_level.txt
linear_matrix-1.0.dist-info/RECORD
