Metadata-Version: 2.2
Name: linear_matrix
Version: 1.0
Summary: A Python library for linear algebra matrix operations.
Home-page: https://sourceduty.com
Author: Sourceduty
Author-email: sourceduty@gmail.com
Classifier: Programming Language :: Python :: 3
Classifier: License :: OSI Approved :: MIT License
Classifier: Operating System :: OS Independent
Requires-Python: >=3.6
Dynamic: author
Dynamic: author-email
Dynamic: classifier
Dynamic: description
Dynamic: description-content-type
Dynamic: home-page
Dynamic: requires-python
Dynamic: summary
